django_unasyncify/__init__.py
django_unasyncify/_codegen.py
django_unasyncify/cmd.py
django_unasyncify/codemod.py
django_unasyncify/config.py
django_unasyncify/py.typed
django_unasyncify/scaffolding.py
django_unasyncify/transform.py
django_unasyncify-0.1.0.dist-info/METADATA
django_unasyncify-0.1.0.dist-info/WHEEL
django_unasyncify-0.1.0.dist-info/entry_points.txt
django_unasyncify-0.1.0.dist-info/licenses/LICENSE
django_unasyncify-0.1.0.dist-info/RECORD
