Metadata-Version: 2.4
Name: django-unasyncify
Version: 0.1.0
Summary: Add your description here
License-File: LICENSE
Requires-Python: >=3.12
Requires-Dist: libcst>=1.6.0
